<?xml version="1.0" encoding="UTF-8"?>
<actions>
        <action>
            <actionName>run</actionName>
            <goals>
                <goal>package</goal>
            </goals>
            <properties>
                <netbeans.deploy>true</netbeans.deploy>
                
                <dspace.config>/home/bitaites/Desktop/pdis/dspace-1.8.2/dspace/target/dspace-1.8.2-build/config/dspace.cfg</dspace.config>
            </properties>
        </action>
        <action>
            <actionName>debug</actionName>
            <goals>
                <goal>package</goal>
            </goals>
            <properties>
                <netbeans.deploy>true</netbeans.deploy>
                <netbeans.deploy.clientUrlPart>/jspui</netbeans.deploy.clientUrlPart>
                <dspace.config>/home/bitaites/Desktop/pdis/dspace-1.8.2/dspace/target/dspace-1.8.2-build/config/dspace.cfg</dspace.config>
                <netbeans.deploy.debugmode>true</netbeans.deploy.debugmode>
            </properties>
        </action>
        <action>
            <actionName>profile</actionName>
            <goals>
                <goal>package</goal>
            </goals>
            <properties>
                <netbeans.deploy>true</netbeans.deploy>
                <netbeans.deploy.clientUrlPart>/jspui</netbeans.deploy.clientUrlPart>
                <netbeans.deploy.profilemode>true</netbeans.deploy.profilemode>
            </properties>
        </action>
    </actions>
